zotero_mcp/__init__.py
zotero_mcp/_version.py
zotero_mcp/cli.py
zotero_mcp/client.py
zotero_mcp/config.py
zotero_mcp/local_db.py
zotero_mcp/py.typed
zotero_mcp/server.py
zotero_mcp/setup_helper.py
zotero_mcp/utils.py
zotero_mcp/default_prompts/__init__.py
zotero_mcp/default_prompts/bibliography_export.md
zotero_mcp/default_prompts/comparative_review.md
zotero_mcp/default_prompts/knowledge_discovery.md
zotero_mcp/default_prompts/literature_review.md
zotero_mcp_lite-0.1.4.dist-info/METADATA
zotero_mcp_lite-0.1.4.dist-info/WHEEL
zotero_mcp_lite-0.1.4.dist-info/entry_points.txt
zotero_mcp_lite-0.1.4.dist-info/licenses/LICENSE
zotero_mcp_lite-0.1.4.dist-info/RECORD
