Metadata-Version: 2.4
Name: zotero-mcp-lite
Version: 0.1.4
Summary: Fast, Customizable & Light Zotero MCP server for AI research assistants
Project-URL: Homepage, https://github.com/xmruuu/zotero-mcp-lite
Project-URL: Bug Tracker, https://github.com/xmruuu/zotero-mcp-lite/issues
Project-URL: Source, https://github.com/xmruuu/zotero-mcp-lite
Author-email: xmruuu <xmruuu@github.com>
License: MIT
License-File: LICENSE
Keywords: ai,claude,cursor,mcp,research,zotero
Classifier: Development Status :: 4 - Beta
Classifier: Intended Audience :: Science/Research
Classifier: License :: OSI Approved :: MIT License
Classifier: Operating System :: OS Independent
Classifier: Programming Language :: Python :: 3
Requires-Python: >=3.10
Requires-Dist: fastmcp>=2.14.0
Requires-Dist: httpx>=0.24.0
Requires-Dist: mistune>=3.0.0
Requires-Dist: packaging>=23.0
Requires-Dist: pymupdf>=1.24.0
Requires-Dist: python-dotenv>=1.0.0
Requires-Dist: pyzotero>=1.5.0
Provides-Extra: dev
Requires-Dist: black>=23.0.0; extra == 'dev'
Requires-Dist: isort>=5.12.0; extra == 'dev'
Requires-Dist: pytest>=7.0.0; extra == 'dev'
